purviewer/__init__.py
purviewer/entra/__init__.py
purviewer/entra/entra_ops.py
purviewer/exchange/__init__.py
purviewer/exchange/exchange_ops.py
purviewer/files/__init__.py
purviewer/files/file_ops.py
purviewer/main.py
purviewer/network/__init__.py
purviewer/network/network_ops.py
purviewer/tools.py
purviewer/users/__init__.py
purviewer/users/user_actions.py
purviewer-0.3.3.dist-info/METADATA
purviewer-0.3.3.dist-info/WHEEL
purviewer-0.3.3.dist-info/entry_points.txt
purviewer-0.3.3.dist-info/licenses/LICENSE
purviewer-0.3.3.dist-info/RECORD
