Metadata-Version: 2.4
Name: purviewer
Version: 0.3.3
Summary: Audit log analyzer for Microsoft Purview
License-Expression: MIT
License-File: LICENSE
Author: Danny Stewart
Author-email: danny@stewart.cc
Requires-Python: >=3.13,<4.0
Classifier: Programming Language :: Python :: 3
Classifier: Programming Language :: Python :: 3.13
Classifier: Programming Language :: Python :: 3.14
Requires-Dist: iplooker (>=0.5.1)
Requires-Dist: numpy (>=2.3.5,<3.0.0)
Requires-Dist: pandas (>=2.3.3,<3.0.0)
Requires-Dist: polykit (>=0.14.6)
Requires-Dist: tabulate (>=0.9.0,<0.10.0)
